azlyrics_scraper/__init__.py
azlyrics_scraper/azlyrics_scraper.py
azlyrics_scraper-1.0.2.dist-info/LICENSE
azlyrics_scraper-1.0.2.dist-info/WHEEL
azlyrics_scraper-1.0.2.dist-info/METADATA
azlyrics_scraper-1.0.2.dist-info/RECORD
