Metadata-Version: 2.1
Name: azlyrics-scraper
Version: 1.0.2
Summary: Search for artists, albums, songs, lyrics on AZLyrics
License: MIT
Author: Adam
Author-email: adam.wilcz7@gmail.com
Requires-Python: >=3.10,<4.0
Classifier: License :: OSI Approved :: MIT License
Classifier: Programming Language :: Python :: 3
Classifier: Programming Language :: Python :: 3.10
Requires-Dist: bs4 (>=0.0.1,<0.0.2)
Requires-Dist: requests (>=2.27.1,<3.0.0)
